{
    "prepare_queue": {
        "installed": [],
        "uninstalled": []
    },
    "config_munge": {
        "files": {}
    },
    "installed_plugins": {
        "cordova-plugin-whitelist": {
            "PACKAGE_NAME": "garethfuller.steffen"
        },
        "cordova-plugin-crosswalk-webview": {
            "PACKAGE_NAME": "garethfuller.steffen"
        },
        "cordova-plugin-splashscreen": {
            "PACKAGE_NAME": "garethfuller.steffen"
        },
        "cordova-plugin-console": {
            "PACKAGE_NAME": "garethfuller.steffen"
        }
    },
    "dependent_plugins": {}
}